bybit_v5_client/__init__.py
bybit_v5_client/bybit_client.py
bybit_v5_client-0.0.6.dist-info/LICENSE.txt
bybit_v5_client-0.0.6.dist-info/METADATA
bybit_v5_client-0.0.6.dist-info/WHEEL
bybit_v5_client-0.0.6.dist-info/RECORD
