Metadata-Version: 2.1
Name: bybit-v5-client
Version: 0.0.6
Summary: Bybit V5 API client
Author: chimpanzee
Author-email: adm@cmpz.dev
Requires-Python: >=3.10,<4.0
Classifier: Programming Language :: Python :: 3
Classifier: Programming Language :: Python :: 3.10
Classifier: Programming Language :: Python :: 3.11
Requires-Dist: requests (>=2.28.2,<3.0.0)
